Metadata-Version: 2.1
Name: cspell
Version: 0.0.1a1
Summary: Context aware spelling check for C/C++ source code files.
Home-page: https://github.com/mdavidsaver/cspell
Author: Michael Davidsaver
Author-email: mdavidsaver@gmail.com
License: GPLv3
Platform: UNKNOWN
Requires-Python: >=3.7
